zs_preflight-0.0.8b0.data/scripts/preflight
zs_preflight-0.0.8b0.data/scripts/zspreflight
zs_preflight-0.0.8b0.dist-info/DESCRIPTION.rst
zs_preflight-0.0.8b0.dist-info/METADATA
zs_preflight-0.0.8b0.dist-info/RECORD
zs_preflight-0.0.8b0.dist-info/WHEEL
zs_preflight-0.0.8b0.dist-info/metadata.json
zs_preflight-0.0.8b0.dist-info/top_level.txt
zspreflight/__init__.py
zspreflight/compute.py
zspreflight/connector.py
zspreflight/host.py
zspreflight/network.py
zspreflight/storage.py
