Metadata-Version: 2.0
Name: zs-preflight
Version: 0.0.8b0
Summary: The ZeroStack preflight check will validate if your hardware is ZeroStack ready.
Home-page: https://github.com/Zerostack-open/zs-preflight.git
Author: Jonathan Arrance
Author-email: jonathan@zerostack.com
License: UNKNOWN
Platform: UNKNOWN
Classifier: Programming Language :: Python :: 2.7
Classifier: Programming Language :: Python :: 3.4
Classifier: Programming Language :: Python :: 3.5
Classifier: License :: OSI Approved :: MIT License
Classifier: Operating System :: OS Independent
Requires-Dist: gspread (>=3.1.0)
Requires-Dist: oauth2client (>=4.1.3)
Requires-Dist: paramiko (>=2.4.2)
